[
    {
        "name": "Skin/Shop/Terrible Tornado/Entities/000000004100.003/000000004100.003.owentity",
        "type": ".OWENTITY file",
        "size": "0.07 KB",
        "dateModified": 1694267337.81602
    },
    {
        "name": "Skin/Shop/Terrible Tornado/Entities/000000004100.003/index.html",
        "type": ".HTML file",
        "size": "2.06 KB",
        "dateModified": 1694713322.4114487
    },
    {
        "name": "Skin/Shop/Terrible Tornado/Entities/000000004100.003/output.json",
        "type": ".JSON file",
        "size": "0.22 KB",
        "dateModified": 1694713322.4104452
    },
    {
        "name": "Skin/Shop/Terrible Tornado/Entities/000000004100.003/script.js",
        "type": ".JS file",
        "size": "3.07 KB",
        "dateModified": 1694713322.4114487
    }
]