[
    {
        "name": "Skin/Battle Pass/Amaterasu/Weapon-1 Crown-1 Hair-1 Color-2/Entities/000000003A47.003/AnimationEffects/000000000073.owanim",
        "type": ".OWANIM file",
        "size": "0.10 KB",
        "dateModified": 1694267279.6305292
    },
    {
        "name": "Skin/Battle Pass/Amaterasu/Weapon-1 Crown-1 Hair-1 Color-2/Entities/000000003A47.003/AnimationEffects/000000000074.owanim",
        "type": ".OWANIM file",
        "size": "0.10 KB",
        "dateModified": 1694267279.6305292
    },
    {
        "name": "Skin/Battle Pass/Amaterasu/Weapon-1 Crown-1 Hair-1 Color-2/Entities/000000003A47.003/AnimationEffects/000000000075.owanim",
        "type": ".OWANIM file",
        "size": "0.10 KB",
        "dateModified": 1694267279.6310291
    },
    {
        "name": "Skin/Battle Pass/Amaterasu/Weapon-1 Crown-1 Hair-1 Color-2/Entities/000000003A47.003/AnimationEffects/000000000076.owanim",
        "type": ".OWANIM file",
        "size": "0.10 KB",
        "dateModified": 1694267279.6310291
    },
    {
        "name": "Skin/Battle Pass/Amaterasu/Weapon-1 Crown-1 Hair-1 Color-2/Entities/000000003A47.003/AnimationEffects/0000000000E9.owanim",
        "type": ".OWANIM file",
        "size": "0.10 KB",
        "dateModified": 1694267279.6310291
    },
    {
        "name": "Skin/Battle Pass/Amaterasu/Weapon-1 Crown-1 Hair-1 Color-2/Entities/000000003A47.003/AnimationEffects/0000000000EA.owanim",
        "type": ".OWANIM file",
        "size": "0.10 KB",
        "dateModified": 1694267279.631529
    },
    {
        "name": "Skin/Battle Pass/Amaterasu/Weapon-1 Crown-1 Hair-1 Color-2/Entities/000000003A47.003/AnimationEffects/0000000000EB.owanim",
        "type": ".OWANIM file",
        "size": "0.10 KB",
        "dateModified": 1694267279.631529
    },
    {
        "name": "Skin/Battle Pass/Amaterasu/Weapon-1 Crown-1 Hair-1 Color-2/Entities/000000003A47.003/AnimationEffects/0000000000EC.owanim",
        "type": ".OWANIM file",
        "size": "0.10 KB",
        "dateModified": 1694267279.632029
    },
    {
        "name": "Skin/Battle Pass/Amaterasu/Weapon-1 Crown-1 Hair-1 Color-2/Entities/000000003A47.003/AnimationEffects/0000000000F2.owanim",
        "type": ".OWANIM file",
        "size": "0.10 KB",
        "dateModified": 1694267279.632029
    },
    {
        "name": "Skin/Battle Pass/Amaterasu/Weapon-1 Crown-1 Hair-1 Color-2/Entities/000000003A47.003/AnimationEffects/0000000000F3.owanim",
        "type": ".OWANIM file",
        "size": "0.10 KB",
        "dateModified": 1694267279.632029
    },
    {
        "name": "Skin/Battle Pass/Amaterasu/Weapon-1 Crown-1 Hair-1 Color-2/Entities/000000003A47.003/AnimationEffects/0000000000F4.owanim",
        "type": ".OWANIM file",
        "size": "0.10 KB",
        "dateModified": 1694267279.632529
    },
    {
        "name": "Skin/Battle Pass/Amaterasu/Weapon-1 Crown-1 Hair-1 Color-2/Entities/000000003A47.003/AnimationEffects/0000000000F5.owanim",
        "type": ".OWANIM file",
        "size": "0.10 KB",
        "dateModified": 1694267279.632529
    },
    {
        "name": "Skin/Battle Pass/Amaterasu/Weapon-1 Crown-1 Hair-1 Color-2/Entities/000000003A47.003/AnimationEffects/0000000000F6.owanim",
        "type": ".OWANIM file",
        "size": "0.10 KB",
        "dateModified": 1694267279.632529
    },
    {
        "name": "Skin/Battle Pass/Amaterasu/Weapon-1 Crown-1 Hair-1 Color-2/Entities/000000003A47.003/AnimationEffects/000000000957.owanim",
        "type": ".OWANIM file",
        "size": "0.10 KB",
        "dateModified": 1694267279.6330297
    },
    {
        "name": "Skin/Battle Pass/Amaterasu/Weapon-1 Crown-1 Hair-1 Color-2/Entities/000000003A47.003/AnimationEffects/000000000958.owanim",
        "type": ".OWANIM file",
        "size": "0.10 KB",
        "dateModified": 1694267279.6330297
    },
    {
        "name": "Skin/Battle Pass/Amaterasu/Weapon-1 Crown-1 Hair-1 Color-2/Entities/000000003A47.003/AnimationEffects/000000000959.owanim",
        "type": ".OWANIM file",
        "size": "0.10 KB",
        "dateModified": 1694267279.6330297
    },
    {
        "name": "Skin/Battle Pass/Amaterasu/Weapon-1 Crown-1 Hair-1 Color-2/Entities/000000003A47.003/AnimationEffects/000000000C4F.owanim",
        "type": ".OWANIM file",
        "size": "0.10 KB",
        "dateModified": 1694267279.6335297
    },
    {
        "name": "Skin/Battle Pass/Amaterasu/Weapon-1 Crown-1 Hair-1 Color-2/Entities/000000003A47.003/AnimationEffects/000000000C63.owanim",
        "type": ".OWANIM file",
        "size": "0.10 KB",
        "dateModified": 1694267279.6335297
    },
    {
        "name": "Skin/Battle Pass/Amaterasu/Weapon-1 Crown-1 Hair-1 Color-2/Entities/000000003A47.003/AnimationEffects/00000000395B.owanim",
        "type": ".OWANIM file",
        "size": "0.10 KB",
        "dateModified": 1694267279.6335297
    },
    {
        "name": "Skin/Battle Pass/Amaterasu/Weapon-1 Crown-1 Hair-1 Color-2/Entities/000000003A47.003/AnimationEffects/000000003B43.owanim",
        "type": ".OWANIM file",
        "size": "0.10 KB",
        "dateModified": 1694267279.6335297
    },
    {
        "name": "Skin/Battle Pass/Amaterasu/Weapon-1 Crown-1 Hair-1 Color-2/Entities/000000003A47.003/AnimationEffects/000000003B44.owanim",
        "type": ".OWANIM file",
        "size": "0.10 KB",
        "dateModified": 1694267279.6335297
    },
    {
        "name": "Skin/Battle Pass/Amaterasu/Weapon-1 Crown-1 Hair-1 Color-2/Entities/000000003A47.003/AnimationEffects/000000003B45.owanim",
        "type": ".OWANIM file",
        "size": "0.10 KB",
        "dateModified": 1694267279.6335297
    },
    {
        "name": "Skin/Battle Pass/Amaterasu/Weapon-1 Crown-1 Hair-1 Color-2/Entities/000000003A47.003/AnimationEffects/000000003B47.owanim",
        "type": ".OWANIM file",
        "size": "0.10 KB",
        "dateModified": 1694267279.6345322
    },
    {
        "name": "Skin/Battle Pass/Amaterasu/Weapon-1 Crown-1 Hair-1 Color-2/Entities/000000003A47.003/AnimationEffects/000000003C97.owanim",
        "type": ".OWANIM file",
        "size": "0.10 KB",
        "dateModified": 1694267279.6345322
    },
    {
        "name": "Skin/Battle Pass/Amaterasu/Weapon-1 Crown-1 Hair-1 Color-2/Entities/000000003A47.003/AnimationEffects/0000000083C9.owanim",
        "type": ".OWANIM file",
        "size": "0.10 KB",
        "dateModified": 1694267279.6345322
    },
    {
        "name": "Skin/Battle Pass/Amaterasu/Weapon-1 Crown-1 Hair-1 Color-2/Entities/000000003A47.003/AnimationEffects/0000000083CA.owanim",
        "type": ".OWANIM file",
        "size": "0.10 KB",
        "dateModified": 1694267279.6350422
    },
    {
        "name": "Skin/Battle Pass/Amaterasu/Weapon-1 Crown-1 Hair-1 Color-2/Entities/000000003A47.003/AnimationEffects/0000000083CB.owanim",
        "type": ".OWANIM file",
        "size": "0.10 KB",
        "dateModified": 1694267279.6350422
    },
    {
        "name": "Skin/Battle Pass/Amaterasu/Weapon-1 Crown-1 Hair-1 Color-2/Entities/000000003A47.003/AnimationEffects/000000008741.owanim",
        "type": ".OWANIM file",
        "size": "0.10 KB",
        "dateModified": 1694267279.6350422
    },
    {
        "name": "Skin/Battle Pass/Amaterasu/Weapon-1 Crown-1 Hair-1 Color-2/Entities/000000003A47.003/AnimationEffects/000000008909.owanim",
        "type": ".OWANIM file",
        "size": "0.10 KB",
        "dateModified": 1694267279.6350422
    },
    {
        "name": "Skin/Battle Pass/Amaterasu/Weapon-1 Crown-1 Hair-1 Color-2/Entities/000000003A47.003/AnimationEffects/00000000A3A7.owanim",
        "type": ".OWANIM file",
        "size": "0.10 KB",
        "dateModified": 1694267279.6355424
    },
    {
        "name": "Skin/Battle Pass/Amaterasu/Weapon-1 Crown-1 Hair-1 Color-2/Entities/000000003A47.003/AnimationEffects/00000000A45D.owanim",
        "type": ".OWANIM file",
        "size": "0.10 KB",
        "dateModified": 1694267279.6355424
    },
    {
        "name": "Skin/Battle Pass/Amaterasu/Weapon-1 Crown-1 Hair-1 Color-2/Entities/000000003A47.003/AnimationEffects/00000000A46E.owanim",
        "type": ".OWANIM file",
        "size": "0.10 KB",
        "dateModified": 1694267279.6355424
    },
    {
        "name": "Skin/Battle Pass/Amaterasu/Weapon-1 Crown-1 Hair-1 Color-2/Entities/000000003A47.003/AnimationEffects/00000000A49C.owanim",
        "type": ".OWANIM file",
        "size": "0.10 KB",
        "dateModified": 1694267279.6355424
    },
    {
        "name": "Skin/Battle Pass/Amaterasu/Weapon-1 Crown-1 Hair-1 Color-2/Entities/000000003A47.003/AnimationEffects/00000000A49D.owanim",
        "type": ".OWANIM file",
        "size": "0.10 KB",
        "dateModified": 1694267279.6364212
    },
    {
        "name": "Skin/Battle Pass/Amaterasu/Weapon-1 Crown-1 Hair-1 Color-2/Entities/000000003A47.003/AnimationEffects/00000000A49E.owanim",
        "type": ".OWANIM file",
        "size": "0.10 KB",
        "dateModified": 1694267279.6364212
    },
    {
        "name": "Skin/Battle Pass/Amaterasu/Weapon-1 Crown-1 Hair-1 Color-2/Entities/000000003A47.003/AnimationEffects/00000000A50A.owanim",
        "type": ".OWANIM file",
        "size": "0.10 KB",
        "dateModified": 1694267279.6364212
    },
    {
        "name": "Skin/Battle Pass/Amaterasu/Weapon-1 Crown-1 Hair-1 Color-2/Entities/000000003A47.003/AnimationEffects/00000000A50B.owanim",
        "type": ".OWANIM file",
        "size": "0.10 KB",
        "dateModified": 1694267279.6369212
    },
    {
        "name": "Skin/Battle Pass/Amaterasu/Weapon-1 Crown-1 Hair-1 Color-2/Entities/000000003A47.003/AnimationEffects/00000000A520.owanim",
        "type": ".OWANIM file",
        "size": "0.10 KB",
        "dateModified": 1694267279.6369212
    },
    {
        "name": "Skin/Battle Pass/Amaterasu/Weapon-1 Crown-1 Hair-1 Color-2/Entities/000000003A47.003/AnimationEffects/00000000A523.owanim",
        "type": ".OWANIM file",
        "size": "0.10 KB",
        "dateModified": 1694267279.6369212
    },
    {
        "name": "Skin/Battle Pass/Amaterasu/Weapon-1 Crown-1 Hair-1 Color-2/Entities/000000003A47.003/AnimationEffects/00000000A524.owanim",
        "type": ".OWANIM file",
        "size": "0.10 KB",
        "dateModified": 1694267279.6374214
    },
    {
        "name": "Skin/Battle Pass/Amaterasu/Weapon-1 Crown-1 Hair-1 Color-2/Entities/000000003A47.003/AnimationEffects/00000000A525.owanim",
        "type": ".OWANIM file",
        "size": "0.10 KB",
        "dateModified": 1694267279.6374214
    },
    {
        "name": "Skin/Battle Pass/Amaterasu/Weapon-1 Crown-1 Hair-1 Color-2/Entities/000000003A47.003/AnimationEffects/00000000A529.owanim",
        "type": ".OWANIM file",
        "size": "0.10 KB",
        "dateModified": 1694267279.6374214
    },
    {
        "name": "Skin/Battle Pass/Amaterasu/Weapon-1 Crown-1 Hair-1 Color-2/Entities/000000003A47.003/AnimationEffects/00000000A591.owanim",
        "type": ".OWANIM file",
        "size": "0.10 KB",
        "dateModified": 1694267279.637921
    },
    {
        "name": "Skin/Battle Pass/Amaterasu/Weapon-1 Crown-1 Hair-1 Color-2/Entities/000000003A47.003/AnimationEffects/00000000A592.owanim",
        "type": ".OWANIM file",
        "size": "0.10 KB",
        "dateModified": 1694267279.637921
    },
    {
        "name": "Skin/Battle Pass/Amaterasu/Weapon-1 Crown-1 Hair-1 Color-2/Entities/000000003A47.003/AnimationEffects/00000000A5F6.owanim",
        "type": ".OWANIM file",
        "size": "0.10 KB",
        "dateModified": 1694267279.637921
    },
    {
        "name": "Skin/Battle Pass/Amaterasu/Weapon-1 Crown-1 Hair-1 Color-2/Entities/000000003A47.003/AnimationEffects/00000000A5F7.owanim",
        "type": ".OWANIM file",
        "size": "0.10 KB",
        "dateModified": 1694267279.6384213
    },
    {
        "name": "Skin/Battle Pass/Amaterasu/Weapon-1 Crown-1 Hair-1 Color-2/Entities/000000003A47.003/AnimationEffects/00000000A6DA.owanim",
        "type": ".OWANIM file",
        "size": "0.10 KB",
        "dateModified": 1694267279.6384213
    },
    {
        "name": "Skin/Battle Pass/Amaterasu/Weapon-1 Crown-1 Hair-1 Color-2/Entities/000000003A47.003/AnimationEffects/00000000A6F7.owanim",
        "type": ".OWANIM file",
        "size": "0.10 KB",
        "dateModified": 1694267279.6384213
    },
    {
        "name": "Skin/Battle Pass/Amaterasu/Weapon-1 Crown-1 Hair-1 Color-2/Entities/000000003A47.003/AnimationEffects/00000000A6F8.owanim",
        "type": ".OWANIM file",
        "size": "0.10 KB",
        "dateModified": 1694267279.6389227
    },
    {
        "name": "Skin/Battle Pass/Amaterasu/Weapon-1 Crown-1 Hair-1 Color-2/Entities/000000003A47.003/AnimationEffects/00000000A810.owanim",
        "type": ".OWANIM file",
        "size": "0.10 KB",
        "dateModified": 1694267279.6389227
    },
    {
        "name": "Skin/Battle Pass/Amaterasu/Weapon-1 Crown-1 Hair-1 Color-2/Entities/000000003A47.003/AnimationEffects/00000000A84C.owanim",
        "type": ".OWANIM file",
        "size": "0.10 KB",
        "dateModified": 1694267279.6394215
    },
    {
        "name": "Skin/Battle Pass/Amaterasu/Weapon-1 Crown-1 Hair-1 Color-2/Entities/000000003A47.003/AnimationEffects/00000000A8F5.owanim",
        "type": ".OWANIM file",
        "size": "0.10 KB",
        "dateModified": 1694267279.6394215
    },
    {
        "name": "Skin/Battle Pass/Amaterasu/Weapon-1 Crown-1 Hair-1 Color-2/Entities/000000003A47.003/AnimationEffects/00000000A8F6.owanim",
        "type": ".OWANIM file",
        "size": "0.10 KB",
        "dateModified": 1694267279.6394215
    },
    {
        "name": "Skin/Battle Pass/Amaterasu/Weapon-1 Crown-1 Hair-1 Color-2/Entities/000000003A47.003/AnimationEffects/00000000A9A9.owanim",
        "type": ".OWANIM file",
        "size": "0.10 KB",
        "dateModified": 1694267279.6399214
    },
    {
        "name": "Skin/Battle Pass/Amaterasu/Weapon-1 Crown-1 Hair-1 Color-2/Entities/000000003A47.003/AnimationEffects/00000000AA48.owanim",
        "type": ".OWANIM file",
        "size": "0.10 KB",
        "dateModified": 1694267279.6399214
    },
    {
        "name": "Skin/Battle Pass/Amaterasu/Weapon-1 Crown-1 Hair-1 Color-2/Entities/000000003A47.003/AnimationEffects/00000000AA7C.owanim",
        "type": ".OWANIM file",
        "size": "0.10 KB",
        "dateModified": 1694267279.6399214
    },
    {
        "name": "Skin/Battle Pass/Amaterasu/Weapon-1 Crown-1 Hair-1 Color-2/Entities/000000003A47.003/AnimationEffects/00000000AA7E.owanim",
        "type": ".OWANIM file",
        "size": "0.10 KB",
        "dateModified": 1694267279.6404214
    },
    {
        "name": "Skin/Battle Pass/Amaterasu/Weapon-1 Crown-1 Hair-1 Color-2/Entities/000000003A47.003/AnimationEffects/00000000AA94.owanim",
        "type": ".OWANIM file",
        "size": "0.10 KB",
        "dateModified": 1694267279.6404214
    },
    {
        "name": "Skin/Battle Pass/Amaterasu/Weapon-1 Crown-1 Hair-1 Color-2/Entities/000000003A47.003/AnimationEffects/00000000AB50.owanim",
        "type": ".OWANIM file",
        "size": "0.10 KB",
        "dateModified": 1694267279.6409223
    },
    {
        "name": "Skin/Battle Pass/Amaterasu/Weapon-1 Crown-1 Hair-1 Color-2/Entities/000000003A47.003/AnimationEffects/00000000AB51.owanim",
        "type": ".OWANIM file",
        "size": "0.10 KB",
        "dateModified": 1694267279.6409223
    },
    {
        "name": "Skin/Battle Pass/Amaterasu/Weapon-1 Crown-1 Hair-1 Color-2/Entities/000000003A47.003/AnimationEffects/00000000AB56.owanim",
        "type": ".OWANIM file",
        "size": "0.10 KB",
        "dateModified": 1694267279.6414223
    },
    {
        "name": "Skin/Battle Pass/Amaterasu/Weapon-1 Crown-1 Hair-1 Color-2/Entities/000000003A47.003/AnimationEffects/00000000AB5C.owanim",
        "type": ".OWANIM file",
        "size": "0.10 KB",
        "dateModified": 1694267279.6414223
    },
    {
        "name": "Skin/Battle Pass/Amaterasu/Weapon-1 Crown-1 Hair-1 Color-2/Entities/000000003A47.003/AnimationEffects/00000000AB7D.owanim",
        "type": ".OWANIM file",
        "size": "0.10 KB",
        "dateModified": 1694267279.6419225
    },
    {
        "name": "Skin/Battle Pass/Amaterasu/Weapon-1 Crown-1 Hair-1 Color-2/Entities/000000003A47.003/AnimationEffects/00000000AB7E.owanim",
        "type": ".OWANIM file",
        "size": "0.10 KB",
        "dateModified": 1694267279.6419225
    },
    {
        "name": "Skin/Battle Pass/Amaterasu/Weapon-1 Crown-1 Hair-1 Color-2/Entities/000000003A47.003/AnimationEffects/00000000AB7F.owanim",
        "type": ".OWANIM file",
        "size": "0.10 KB",
        "dateModified": 1694267279.6424267
    },
    {
        "name": "Skin/Battle Pass/Amaterasu/Weapon-1 Crown-1 Hair-1 Color-2/Entities/000000003A47.003/AnimationEffects/00000000ABCD.owanim",
        "type": ".OWANIM file",
        "size": "0.10 KB",
        "dateModified": 1694267279.6429276
    },
    {
        "name": "Skin/Battle Pass/Amaterasu/Weapon-1 Crown-1 Hair-1 Color-2/Entities/000000003A47.003/AnimationEffects/00000000ABCE.owanim",
        "type": ".OWANIM file",
        "size": "0.10 KB",
        "dateModified": 1694267279.6429276
    },
    {
        "name": "Skin/Battle Pass/Amaterasu/Weapon-1 Crown-1 Hair-1 Color-2/Entities/000000003A47.003/AnimationEffects/00000000ABEB.owanim",
        "type": ".OWANIM file",
        "size": "0.10 KB",
        "dateModified": 1694267279.6469488
    },
    {
        "name": "Skin/Battle Pass/Amaterasu/Weapon-1 Crown-1 Hair-1 Color-2/Entities/000000003A47.003/AnimationEffects/00000000ABED.owanim",
        "type": ".OWANIM file",
        "size": "0.10 KB",
        "dateModified": 1694267279.6469488
    },
    {
        "name": "Skin/Battle Pass/Amaterasu/Weapon-1 Crown-1 Hair-1 Color-2/Entities/000000003A47.003/AnimationEffects/00000000ABEE.owanim",
        "type": ".OWANIM file",
        "size": "0.10 KB",
        "dateModified": 1694267279.6469488
    },
    {
        "name": "Skin/Battle Pass/Amaterasu/Weapon-1 Crown-1 Hair-1 Color-2/Entities/000000003A47.003/AnimationEffects/00000000AC79.owanim",
        "type": ".OWANIM file",
        "size": "0.10 KB",
        "dateModified": 1694267279.647449
    },
    {
        "name": "Skin/Battle Pass/Amaterasu/Weapon-1 Crown-1 Hair-1 Color-2/Entities/000000003A47.003/AnimationEffects/00000000AED0.owanim",
        "type": ".OWANIM file",
        "size": "0.10 KB",
        "dateModified": 1694267279.647449
    },
    {
        "name": "Skin/Battle Pass/Amaterasu/Weapon-1 Crown-1 Hair-1 Color-2/Entities/000000003A47.003/AnimationEffects/00000000AEF6.owanim",
        "type": ".OWANIM file",
        "size": "0.10 KB",
        "dateModified": 1694267279.647449
    },
    {
        "name": "Skin/Battle Pass/Amaterasu/Weapon-1 Crown-1 Hair-1 Color-2/Entities/000000003A47.003/AnimationEffects/00000000AEF7.owanim",
        "type": ".OWANIM file",
        "size": "0.10 KB",
        "dateModified": 1694267279.6479492
    },
    {
        "name": "Skin/Battle Pass/Amaterasu/Weapon-1 Crown-1 Hair-1 Color-2/Entities/000000003A47.003/AnimationEffects/00000000AEF8.owanim",
        "type": ".OWANIM file",
        "size": "0.10 KB",
        "dateModified": 1694267279.6479492
    },
    {
        "name": "Skin/Battle Pass/Amaterasu/Weapon-1 Crown-1 Hair-1 Color-2/Entities/000000003A47.003/AnimationEffects/00000000AEF9.owanim",
        "type": ".OWANIM file",
        "size": "0.10 KB",
        "dateModified": 1694267279.6479492
    },
    {
        "name": "Skin/Battle Pass/Amaterasu/Weapon-1 Crown-1 Hair-1 Color-2/Entities/000000003A47.003/AnimationEffects/00000000AF02.owanim",
        "type": ".OWANIM file",
        "size": "0.10 KB",
        "dateModified": 1694267279.6484492
    },
    {
        "name": "Skin/Battle Pass/Amaterasu/Weapon-1 Crown-1 Hair-1 Color-2/Entities/000000003A47.003/AnimationEffects/00000000AF03.owanim",
        "type": ".OWANIM file",
        "size": "0.10 KB",
        "dateModified": 1694267279.6484492
    },
    {
        "name": "Skin/Battle Pass/Amaterasu/Weapon-1 Crown-1 Hair-1 Color-2/Entities/000000003A47.003/AnimationEffects/00000000AF49.owanim",
        "type": ".OWANIM file",
        "size": "0.10 KB",
        "dateModified": 1694267279.6484492
    },
    {
        "name": "Skin/Battle Pass/Amaterasu/Weapon-1 Crown-1 Hair-1 Color-2/Entities/000000003A47.003/AnimationEffects/00000000AFCE.owanim",
        "type": ".OWANIM file",
        "size": "0.10 KB",
        "dateModified": 1694267279.6489494
    },
    {
        "name": "Skin/Battle Pass/Amaterasu/Weapon-1 Crown-1 Hair-1 Color-2/Entities/000000003A47.003/AnimationEffects/00000000B088.owanim",
        "type": ".OWANIM file",
        "size": "0.10 KB",
        "dateModified": 1694267279.6489494
    },
    {
        "name": "Skin/Battle Pass/Amaterasu/Weapon-1 Crown-1 Hair-1 Color-2/Entities/000000003A47.003/AnimationEffects/00000000B0E1.owanim",
        "type": ".OWANIM file",
        "size": "0.10 KB",
        "dateModified": 1694267279.6489494
    },
    {
        "name": "Skin/Battle Pass/Amaterasu/Weapon-1 Crown-1 Hair-1 Color-2/Entities/000000003A47.003/AnimationEffects/00000000B0F0.owanim",
        "type": ".OWANIM file",
        "size": "0.10 KB",
        "dateModified": 1694267279.6494493
    },
    {
        "name": "Skin/Battle Pass/Amaterasu/Weapon-1 Crown-1 Hair-1 Color-2/Entities/000000003A47.003/AnimationEffects/00000000B1D0.owanim",
        "type": ".OWANIM file",
        "size": "0.10 KB",
        "dateModified": 1694267279.6494493
    },
    {
        "name": "Skin/Battle Pass/Amaterasu/Weapon-1 Crown-1 Hair-1 Color-2/Entities/000000003A47.003/AnimationEffects/00000000B1D6.owanim",
        "type": ".OWANIM file",
        "size": "0.10 KB",
        "dateModified": 1694267279.650449
    },
    {
        "name": "Skin/Battle Pass/Amaterasu/Weapon-1 Crown-1 Hair-1 Color-2/Entities/000000003A47.003/AnimationEffects/00000000C52C.owanim",
        "type": ".OWANIM file",
        "size": "0.10 KB",
        "dateModified": 1694267279.650449
    },
    {
        "name": "Skin/Battle Pass/Amaterasu/Weapon-1 Crown-1 Hair-1 Color-2/Entities/000000003A47.003/AnimationEffects/00000000C52D.owanim",
        "type": ".OWANIM file",
        "size": "0.10 KB",
        "dateModified": 1694267279.650949
    },
    {
        "name": "Skin/Battle Pass/Amaterasu/Weapon-1 Crown-1 Hair-1 Color-2/Entities/000000003A47.003/AnimationEffects/00000000C534.owanim",
        "type": ".OWANIM file",
        "size": "0.10 KB",
        "dateModified": 1694267279.650949
    },
    {
        "name": "Skin/Battle Pass/Amaterasu/Weapon-1 Crown-1 Hair-1 Color-2/Entities/000000003A47.003/AnimationEffects/00000000C535.owanim",
        "type": ".OWANIM file",
        "size": "0.10 KB",
        "dateModified": 1694267279.650949
    },
    {
        "name": "Skin/Battle Pass/Amaterasu/Weapon-1 Crown-1 Hair-1 Color-2/Entities/000000003A47.003/AnimationEffects/00000000C536.owanim",
        "type": ".OWANIM file",
        "size": "0.10 KB",
        "dateModified": 1694267279.651449
    },
    {
        "name": "Skin/Battle Pass/Amaterasu/Weapon-1 Crown-1 Hair-1 Color-2/Entities/000000003A47.003/AnimationEffects/00000000C537.owanim",
        "type": ".OWANIM file",
        "size": "0.10 KB",
        "dateModified": 1694267279.651449
    }
]