[
    {
        "name": "Overwatch/Anqas/Models/000000000801.00C/Textures/000000000242.png",
        "type": ".PNG file",
        "size": "3.46 KB",
        "dateModified": 1694621455.81506
    },
    {
        "name": "Overwatch/Anqas/Models/000000000801.00C/Textures/0000000004DB.png",
        "type": ".PNG file",
        "size": "36.27 KB",
        "dateModified": 1694621455.8337119
    },
    {
        "name": "Overwatch/Anqas/Models/000000000801.00C/Textures/0000000005D0.png",
        "type": ".PNG file",
        "size": "17.47 KB",
        "dateModified": 1694621455.847385
    },
    {
        "name": "Overwatch/Anqas/Models/000000000801.00C/Textures/0000000005DF.png",
        "type": ".PNG file",
        "size": "34.42 KB",
        "dateModified": 1694621455.8689754
    },
    {
        "name": "Overwatch/Anqas/Models/000000000801.00C/Textures/0000000007AB.png",
        "type": ".PNG file",
        "size": "36.09 KB",
        "dateModified": 1694621455.8885539
    },
    {
        "name": "Overwatch/Anqas/Models/000000000801.00C/Textures/000000000AFF.png",
        "type": ".PNG file",
        "size": "47.10 KB",
        "dateModified": 1694621455.9102147
    },
    {
        "name": "Overwatch/Anqas/Models/000000000801.00C/Textures/000000000B08.png",
        "type": ".PNG file",
        "size": "38.46 KB",
        "dateModified": 1694621455.92837
    },
    {
        "name": "Overwatch/Anqas/Models/000000000801.00C/Textures/000000000B0B.png",
        "type": ".PNG file",
        "size": "41.93 KB",
        "dateModified": 1694621455.94688
    },
    {
        "name": "Overwatch/Anqas/Models/000000000801.00C/Textures/000000000D8F.png",
        "type": ".PNG file",
        "size": "18.74 KB",
        "dateModified": 1694621455.9553387
    },
    {
        "name": "Overwatch/Anqas/Models/000000000801.00C/Textures/0000000010A3.png",
        "type": ".PNG file",
        "size": "0.09 KB",
        "dateModified": 1694621455.9583423
    },
    {
        "name": "Overwatch/Anqas/Models/000000000801.00C/Textures/000000001268.png",
        "type": ".PNG file",
        "size": "33.38 KB",
        "dateModified": 1694621455.9763367
    },
    {
        "name": "Overwatch/Anqas/Models/000000000801.00C/Textures/000000001369.png",
        "type": ".PNG file",
        "size": "13.10 KB",
        "dateModified": 1694621455.9873805
    },
    {
        "name": "Overwatch/Anqas/Models/000000000801.00C/Textures/000000001395.png",
        "type": ".PNG file",
        "size": "0.61 KB",
        "dateModified": 1694621455.9928954
    },
    {
        "name": "Overwatch/Anqas/Models/000000000801.00C/Textures/00000000139C.png",
        "type": ".PNG file",
        "size": "15.45 KB",
        "dateModified": 1694621456.003927
    },
    {
        "name": "Overwatch/Anqas/Models/000000000801.00C/Textures/0000000017D8.png",
        "type": ".PNG file",
        "size": "41.79 KB",
        "dateModified": 1694621456.023056
    },
    {
        "name": "Overwatch/Anqas/Models/000000000801.00C/Textures/000000002585.png",
        "type": ".PNG file",
        "size": "51.47 KB",
        "dateModified": 1694621456.0627975
    },
    {
        "name": "Overwatch/Anqas/Models/000000000801.00C/Textures/000000004C09.png",
        "type": ".PNG file",
        "size": "15.33 KB",
        "dateModified": 1694621456.0872488
    },
    {
        "name": "Overwatch/Anqas/Models/000000000801.00C/Textures/000000005AA0.png",
        "type": ".PNG file",
        "size": "0.29 KB",
        "dateModified": 1694621456.0983741
    },
    {
        "name": "Overwatch/Anqas/Models/000000000801.00C/Textures/000000007ADC.png",
        "type": ".PNG file",
        "size": "1.28 KB",
        "dateModified": 1694621456.104255
    },
    {
        "name": "Overwatch/Anqas/Models/000000000801.00C/Textures/000000009F81.png",
        "type": ".PNG file",
        "size": "25.03 KB",
        "dateModified": 1694621456.1228695
    },
    {
        "name": "Overwatch/Anqas/Models/000000000801.00C/Textures/00000000A06C.png",
        "type": ".PNG file",
        "size": "0.31 KB",
        "dateModified": 1694621456.124888
    },
    {
        "name": "Overwatch/Anqas/Models/000000000801.00C/Textures/00000000A4EC.png",
        "type": ".PNG file",
        "size": "67.11 KB",
        "dateModified": 1694621456.151364
    },
    {
        "name": "Overwatch/Anqas/Models/000000000801.00C/Textures/00000000A4ED.png",
        "type": ".PNG file",
        "size": "132.67 KB",
        "dateModified": 1694621456.1873336
    },
    {
        "name": "Overwatch/Anqas/Models/000000000801.00C/Textures/00000000A720.png",
        "type": ".PNG file",
        "size": "0.32 KB",
        "dateModified": 1694621456.1893504
    },
    {
        "name": "Overwatch/Anqas/Models/000000000801.00C/Textures/00000000A7B6.png",
        "type": ".PNG file",
        "size": "13.16 KB",
        "dateModified": 1694621456.197233
    },
    {
        "name": "Overwatch/Anqas/Models/000000000801.00C/Textures/00000000AB9D.png",
        "type": ".PNG file",
        "size": "16.18 KB",
        "dateModified": 1694621456.2027302
    },
    {
        "name": "Overwatch/Anqas/Models/000000000801.00C/Textures/00000000ADD0.png",
        "type": ".PNG file",
        "size": "0.36 KB",
        "dateModified": 1694621456.2041109
    },
    {
        "name": "Overwatch/Anqas/Models/000000000801.00C/Textures/00000000ADDD.png",
        "type": ".PNG file",
        "size": "0.30 KB",
        "dateModified": 1694621456.205111
    },
    {
        "name": "Overwatch/Anqas/Models/000000000801.00C/Textures/00000000AEF7.png",
        "type": ".PNG file",
        "size": "0.12 KB",
        "dateModified": 1694621456.2061112
    },
    {
        "name": "Overwatch/Anqas/Models/000000000801.00C/Textures/00000000CC29.png",
        "type": ".PNG file",
        "size": "19.18 KB",
        "dateModified": 1694621456.2168076
    },
    {
        "name": "Overwatch/Anqas/Models/000000000801.00C/Textures/000000018B18.png",
        "type": ".PNG file",
        "size": "12.91 KB",
        "dateModified": 1694621456.2289212
    },
    {
        "name": "Overwatch/Anqas/Models/000000000801.00C/Textures/000000018BC2.png",
        "type": ".PNG file",
        "size": "1.24 KB",
        "dateModified": 1694621456.2347646
    },
    {
        "name": "Overwatch/Anqas/Models/000000000801.00C/Textures/000000018BC2_1.png",
        "type": ".PNG file",
        "size": "1.17 KB",
        "dateModified": 1694621456.2397845
    },
    {
        "name": "Overwatch/Anqas/Models/000000000801.00C/Textures/000000018BC2_2.png",
        "type": ".PNG file",
        "size": "1.15 KB",
        "dateModified": 1694621456.2452593
    },
    {
        "name": "Overwatch/Anqas/Models/000000000801.00C/Textures/000000018BC2_3.png",
        "type": ".PNG file",
        "size": "1.21 KB",
        "dateModified": 1694621456.250274
    },
    {
        "name": "Overwatch/Anqas/Models/000000000801.00C/Textures/000000018E48.png",
        "type": ".PNG file",
        "size": "7.58 KB",
        "dateModified": 1694621456.2567892
    },
    {
        "name": "Overwatch/Anqas/Models/000000000801.00C/Textures/000000019167.png",
        "type": ".PNG file",
        "size": "10.83 KB",
        "dateModified": 1694621456.2663207
    },
    {
        "name": "Overwatch/Anqas/Models/000000000801.00C/Textures/00000001CAFA.png",
        "type": ".PNG file",
        "size": "16.01 KB",
        "dateModified": 1694621456.2748547
    },
    {
        "name": "Overwatch/Anqas/Models/000000000801.00C/Textures/00000001CB44.png",
        "type": ".PNG file",
        "size": "2.91 KB",
        "dateModified": 1694621456.2773547
    },
    {
        "name": "Overwatch/Anqas/Models/000000000801.00C/Textures/00000001CB44_1.png",
        "type": ".PNG file",
        "size": "2.17 KB",
        "dateModified": 1694621456.2783568
    },
    {
        "name": "Overwatch/Anqas/Models/000000000801.00C/Textures/00000001CB44_2.png",
        "type": ".PNG file",
        "size": "1.23 KB",
        "dateModified": 1694621456.279868
    },
    {
        "name": "Overwatch/Anqas/Models/000000000801.00C/Textures/00000001CB44_3.png",
        "type": ".PNG file",
        "size": "1.80 KB",
        "dateModified": 1694621456.2813685
    },
    {
        "name": "Overwatch/Anqas/Models/000000000801.00C/Textures/00000001DFCB.png",
        "type": ".PNG file",
        "size": "18.74 KB",
        "dateModified": 1694621456.2894056
    },
    {
        "name": "Overwatch/Anqas/Models/000000000801.00C/Textures/00000001DFCB_1.png",
        "type": ".PNG file",
        "size": "18.65 KB",
        "dateModified": 1694621456.2972784
    },
    {
        "name": "Overwatch/Anqas/Models/000000000801.00C/Textures/00000001DFCB_10.png",
        "type": ".PNG file",
        "size": "20.07 KB",
        "dateModified": 1694621456.30621
    },
    {
        "name": "Overwatch/Anqas/Models/000000000801.00C/Textures/00000001DFCB_11.png",
        "type": ".PNG file",
        "size": "19.87 KB",
        "dateModified": 1694621456.3172727
    },
    {
        "name": "Overwatch/Anqas/Models/000000000801.00C/Textures/00000001DFCB_12.png",
        "type": ".PNG file",
        "size": "20.15 KB",
        "dateModified": 1694621456.3272896
    },
    {
        "name": "Overwatch/Anqas/Models/000000000801.00C/Textures/00000001DFCB_13.png",
        "type": ".PNG file",
        "size": "19.98 KB",
        "dateModified": 1694621456.3403406
    },
    {
        "name": "Overwatch/Anqas/Models/000000000801.00C/Textures/00000001DFCB_14.png",
        "type": ".PNG file",
        "size": "20.07 KB",
        "dateModified": 1694621456.3528695
    },
    {
        "name": "Overwatch/Anqas/Models/000000000801.00C/Textures/00000001DFCB_15.png",
        "type": ".PNG file",
        "size": "19.97 KB",
        "dateModified": 1694621456.3674328
    },
    {
        "name": "Overwatch/Anqas/Models/000000000801.00C/Textures/00000001DFCB_16.png",
        "type": ".PNG file",
        "size": "20.10 KB",
        "dateModified": 1694621456.3830063
    },
    {
        "name": "Overwatch/Anqas/Models/000000000801.00C/Textures/00000001DFCB_17.png",
        "type": ".PNG file",
        "size": "20.75 KB",
        "dateModified": 1694621456.3971
    },
    {
        "name": "Overwatch/Anqas/Models/000000000801.00C/Textures/00000001DFCB_18.png",
        "type": ".PNG file",
        "size": "20.41 KB",
        "dateModified": 1694621456.4116807
    },
    {
        "name": "Overwatch/Anqas/Models/000000000801.00C/Textures/00000001DFCB_19.png",
        "type": ".PNG file",
        "size": "20.19 KB",
        "dateModified": 1694621456.4253142
    },
    {
        "name": "Overwatch/Anqas/Models/000000000801.00C/Textures/00000001DFCB_2.png",
        "type": ".PNG file",
        "size": "18.38 KB",
        "dateModified": 1694621456.432829
    },
    {
        "name": "Overwatch/Anqas/Models/000000000801.00C/Textures/00000001DFCB_20.png",
        "type": ".PNG file",
        "size": "20.38 KB",
        "dateModified": 1694621456.447374
    },
    {
        "name": "Overwatch/Anqas/Models/000000000801.00C/Textures/00000001DFCB_21.png",
        "type": ".PNG file",
        "size": "20.00 KB",
        "dateModified": 1694621456.4604218
    },
    {
        "name": "Overwatch/Anqas/Models/000000000801.00C/Textures/00000001DFCB_22.png",
        "type": ".PNG file",
        "size": "20.46 KB",
        "dateModified": 1694621456.4749713
    },
    {
        "name": "Overwatch/Anqas/Models/000000000801.00C/Textures/00000001DFCB_23.png",
        "type": ".PNG file",
        "size": "20.02 KB",
        "dateModified": 1694621456.4885156
    },
    {
        "name": "Overwatch/Anqas/Models/000000000801.00C/Textures/00000001DFCB_24.png",
        "type": ".PNG file",
        "size": "19.90 KB",
        "dateModified": 1694621456.5025551
    },
    {
        "name": "Overwatch/Anqas/Models/000000000801.00C/Textures/00000001DFCB_25.png",
        "type": ".PNG file",
        "size": "19.92 KB",
        "dateModified": 1694621456.515704
    },
    {
        "name": "Overwatch/Anqas/Models/000000000801.00C/Textures/00000001DFCB_26.png",
        "type": ".PNG file",
        "size": "19.89 KB",
        "dateModified": 1694621456.5293226
    },
    {
        "name": "Overwatch/Anqas/Models/000000000801.00C/Textures/00000001DFCB_27.png",
        "type": ".PNG file",
        "size": "19.72 KB",
        "dateModified": 1694621456.54379
    },
    {
        "name": "Overwatch/Anqas/Models/000000000801.00C/Textures/00000001DFCB_28.png",
        "type": ".PNG file",
        "size": "19.40 KB",
        "dateModified": 1694621456.5564477
    },
    {
        "name": "Overwatch/Anqas/Models/000000000801.00C/Textures/00000001DFCB_29.png",
        "type": ".PNG file",
        "size": "18.91 KB",
        "dateModified": 1694621456.5694902
    },
    {
        "name": "Overwatch/Anqas/Models/000000000801.00C/Textures/00000001DFCB_3.png",
        "type": ".PNG file",
        "size": "18.65 KB",
        "dateModified": 1694621456.5772734
    },
    {
        "name": "Overwatch/Anqas/Models/000000000801.00C/Textures/00000001DFCB_30.png",
        "type": ".PNG file",
        "size": "19.05 KB",
        "dateModified": 1694621456.590428
    },
    {
        "name": "Overwatch/Anqas/Models/000000000801.00C/Textures/00000001DFCB_31.png",
        "type": ".PNG file",
        "size": "18.79 KB",
        "dateModified": 1694621456.6029582
    },
    {
        "name": "Overwatch/Anqas/Models/000000000801.00C/Textures/00000001DFCB_4.png",
        "type": ".PNG file",
        "size": "18.90 KB",
        "dateModified": 1694621456.6119874
    },
    {
        "name": "Overwatch/Anqas/Models/000000000801.00C/Textures/00000001DFCB_5.png",
        "type": ".PNG file",
        "size": "19.17 KB",
        "dateModified": 1694621456.6208386
    },
    {
        "name": "Overwatch/Anqas/Models/000000000801.00C/Textures/00000001DFCB_6.png",
        "type": ".PNG file",
        "size": "19.02 KB",
        "dateModified": 1694621456.629364
    },
    {
        "name": "Overwatch/Anqas/Models/000000000801.00C/Textures/00000001DFCB_7.png",
        "type": ".PNG file",
        "size": "19.20 KB",
        "dateModified": 1694621456.6381872
    },
    {
        "name": "Overwatch/Anqas/Models/000000000801.00C/Textures/00000001DFCB_8.png",
        "type": ".PNG file",
        "size": "19.23 KB",
        "dateModified": 1694621456.648221
    },
    {
        "name": "Overwatch/Anqas/Models/000000000801.00C/Textures/00000001DFCB_9.png",
        "type": ".PNG file",
        "size": "19.41 KB",
        "dateModified": 1694621456.656229
    },
    {
        "name": "Overwatch/Anqas/Models/000000000801.00C/Textures/00000001EDB3.png",
        "type": ".PNG file",
        "size": "14.43 KB",
        "dateModified": 1694621456.6672628
    },
    {
        "name": "Overwatch/Anqas/Models/000000000801.00C/Textures/00000002007A.png",
        "type": ".PNG file",
        "size": "13.92 KB",
        "dateModified": 1694621456.6772964
    },
    {
        "name": "Overwatch/Anqas/Models/000000000801.00C/Textures/000000029059.png",
        "type": ".PNG file",
        "size": "7.88 KB",
        "dateModified": 1694621456.685384
    },
    {
        "name": "Overwatch/Anqas/Models/000000000801.00C/Textures/000000029267.png",
        "type": ".PNG file",
        "size": "2.90 KB",
        "dateModified": 1694621456.6911957
    },
    {
        "name": "Overwatch/Anqas/Models/000000000801.00C/Textures/000000029267_1.png",
        "type": ".PNG file",
        "size": "3.12 KB",
        "dateModified": 1694621456.6972632
    },
    {
        "name": "Overwatch/Anqas/Models/000000000801.00C/Textures/000000029267_2.png",
        "type": ".PNG file",
        "size": "3.16 KB",
        "dateModified": 1694621456.7027783
    },
    {
        "name": "Overwatch/Anqas/Models/000000000801.00C/Textures/00000002C8D0.png",
        "type": ".PNG file",
        "size": "2.27 KB",
        "dateModified": 1694621456.7108257
    },
    {
        "name": "Overwatch/Anqas/Models/000000000801.00C/Textures/00000002D0A5.png",
        "type": ".PNG file",
        "size": "32.61 KB",
        "dateModified": 1694621456.7329452
    },
    {
        "name": "Overwatch/Anqas/Models/000000000801.00C/Textures/00000002FF5B.png",
        "type": ".PNG file",
        "size": "55.81 KB",
        "dateModified": 1694621456.7762318
    },
    {
        "name": "Overwatch/Anqas/Models/000000000801.00C/Textures/00000002FF5B_1.png",
        "type": ".PNG file",
        "size": "59.85 KB",
        "dateModified": 1694621456.8184552
    },
    {
        "name": "Overwatch/Anqas/Models/000000000801.00C/Textures/00000002FF5B_2.png",
        "type": ".PNG file",
        "size": "55.49 KB",
        "dateModified": 1694621456.8627102
    },
    {
        "name": "Overwatch/Anqas/Models/000000000801.00C/Textures/000000039E7E.png",
        "type": ".PNG file",
        "size": "0.08 KB",
        "dateModified": 1694621456.868277
    },
    {
        "name": "Overwatch/Anqas/Models/000000000801.00C/Textures/00000003E45B.png",
        "type": ".PNG file",
        "size": "64.31 KB",
        "dateModified": 1694621456.913047
    },
    {
        "name": "Overwatch/Anqas/Models/000000000801.00C/Textures/00000003FAA8.png",
        "type": ".PNG file",
        "size": "15.48 KB",
        "dateModified": 1694621456.9598057
    },
    {
        "name": "Overwatch/Anqas/Models/000000000801.00C/Textures/00000004174D.png",
        "type": ".PNG file",
        "size": "2.32 KB",
        "dateModified": 1694621456.9658196
    },
    {
        "name": "Overwatch/Anqas/Models/000000000801.00C/Textures/000000042CE5.png",
        "type": ".PNG file",
        "size": "26.16 KB",
        "dateModified": 1694621456.9843915
    },
    {
        "name": "Overwatch/Anqas/Models/000000000801.00C/Textures/000000043321.png",
        "type": ".PNG file",
        "size": "20.71 KB",
        "dateModified": 1694621457.0013425
    },
    {
        "name": "Overwatch/Anqas/Models/000000000801.00C/Textures/80000555E9A4.png",
        "type": ".PNG file",
        "size": "0.36 KB",
        "dateModified": 1694621457.0029294
    },
    {
        "name": "Overwatch/Anqas/Models/000000000801.00C/Textures/800007DC4BBA.png",
        "type": ".PNG file",
        "size": "0.12 KB",
        "dateModified": 1694621457.0039322
    },
    {
        "name": "Overwatch/Anqas/Models/000000000801.00C/Textures/80000D1482C2.png",
        "type": ".PNG file",
        "size": "0.27 KB",
        "dateModified": 1694621457.0050254
    },
    {
        "name": "Overwatch/Anqas/Models/000000000801.00C/Textures/80000E927A3B.png",
        "type": ".PNG file",
        "size": "0.17 KB",
        "dateModified": 1694621457.0065255
    },
    {
        "name": "Overwatch/Anqas/Models/000000000801.00C/Textures/8000163969D0.png",
        "type": ".PNG file",
        "size": "0.23 KB",
        "dateModified": 1694621457.0075269
    },
    {
        "name": "Overwatch/Anqas/Models/000000000801.00C/Textures/80001A56F30C.png",
        "type": ".PNG file",
        "size": "0.35 KB",
        "dateModified": 1694621457.009044
    },
    {
        "name": "Overwatch/Anqas/Models/000000000801.00C/Textures/80001DCCBDC5.png",
        "type": ".PNG file",
        "size": "0.27 KB",
        "dateModified": 1694621457.0095441
    },
    {
        "name": "Overwatch/Anqas/Models/000000000801.00C/Textures/80001EB98C8C.png",
        "type": ".PNG file",
        "size": "0.19 KB",
        "dateModified": 1694621457.0113752
    },
    {
        "name": "Overwatch/Anqas/Models/000000000801.00C/Textures/80002076BB2D.png",
        "type": ".PNG file",
        "size": "0.12 KB",
        "dateModified": 1694621457.012376
    },
    {
        "name": "Overwatch/Anqas/Models/000000000801.00C/Textures/800028B0E938.png",
        "type": ".PNG file",
        "size": "0.22 KB",
        "dateModified": 1694621457.0128767
    },
    {
        "name": "Overwatch/Anqas/Models/000000000801.00C/Textures/80002AAD736B.png",
        "type": ".PNG file",
        "size": "0.18 KB",
        "dateModified": 1694621457.0138795
    },
    {
        "name": "Overwatch/Anqas/Models/000000000801.00C/Textures/80002AB5E2E7.png",
        "type": ".PNG file",
        "size": "0.19 KB",
        "dateModified": 1694621457.0148895
    },
    {
        "name": "Overwatch/Anqas/Models/000000000801.00C/Textures/800034739082.png",
        "type": ".PNG file",
        "size": "0.41 KB",
        "dateModified": 1694621457.01589
    },
    {
        "name": "Overwatch/Anqas/Models/000000000801.00C/Textures/80003950A64A.png",
        "type": ".PNG file",
        "size": "0.21 KB",
        "dateModified": 1694621457.0173898
    },
    {
        "name": "Overwatch/Anqas/Models/000000000801.00C/Textures/80003A3C0837.png",
        "type": ".PNG file",
        "size": "0.28 KB",
        "dateModified": 1694621457.018392
    },
    {
        "name": "Overwatch/Anqas/Models/000000000801.00C/Textures/80003FA8683C.png",
        "type": ".PNG file",
        "size": "0.27 KB",
        "dateModified": 1694621457.0204027
    },
    {
        "name": "Overwatch/Anqas/Models/000000000801.00C/Textures/800043044062.png",
        "type": ".PNG file",
        "size": "0.21 KB",
        "dateModified": 1694621457.0214021
    },
    {
        "name": "Overwatch/Anqas/Models/000000000801.00C/Textures/80004533FB70.png",
        "type": ".PNG file",
        "size": "0.16 KB",
        "dateModified": 1694621457.0224035
    },
    {
        "name": "Overwatch/Anqas/Models/000000000801.00C/Textures/800046E2C2EB.png",
        "type": ".PNG file",
        "size": "0.21 KB",
        "dateModified": 1694621457.0229337
    },
    {
        "name": "Overwatch/Anqas/Models/000000000801.00C/Textures/8000479EC7F1.png",
        "type": ".PNG file",
        "size": "0.08 KB",
        "dateModified": 1694621457.0249505
    },
    {
        "name": "Overwatch/Anqas/Models/000000000801.00C/Textures/80004A490EDB.png",
        "type": ".PNG file",
        "size": "0.22 KB",
        "dateModified": 1694621457.025951
    },
    {
        "name": "Overwatch/Anqas/Models/000000000801.00C/Textures/80005187EEF2.png",
        "type": ".PNG file",
        "size": "0.20 KB",
        "dateModified": 1694621457.0269516
    },
    {
        "name": "Overwatch/Anqas/Models/000000000801.00C/Textures/800058E4140D.png",
        "type": ".PNG file",
        "size": "0.19 KB",
        "dateModified": 1694621457.0274508
    },
    {
        "name": "Overwatch/Anqas/Models/000000000801.00C/Textures/800062C9304F.png",
        "type": ".PNG file",
        "size": "0.38 KB",
        "dateModified": 1694621457.029464
    },
    {
        "name": "Overwatch/Anqas/Models/000000000801.00C/Textures/800062D5F924.png",
        "type": ".PNG file",
        "size": "0.34 KB",
        "dateModified": 1694621457.0301394
    },
    {
        "name": "Overwatch/Anqas/Models/000000000801.00C/Textures/8000641C8D8C.png",
        "type": ".PNG file",
        "size": "0.40 KB",
        "dateModified": 1694621457.0316393
    },
    {
        "name": "Overwatch/Anqas/Models/000000000801.00C/Textures/8000677E97E0.png",
        "type": ".PNG file",
        "size": "0.19 KB",
        "dateModified": 1694621457.0321398
    },
    {
        "name": "Overwatch/Anqas/Models/000000000801.00C/Textures/80006BCAD0B3.png",
        "type": ".PNG file",
        "size": "0.14 KB",
        "dateModified": 1694621457.0336413
    },
    {
        "name": "Overwatch/Anqas/Models/000000000801.00C/Textures/800072186B5D.png",
        "type": ".PNG file",
        "size": "0.20 KB",
        "dateModified": 1694621457.034153
    },
    {
        "name": "Overwatch/Anqas/Models/000000000801.00C/Textures/800075462B70.png",
        "type": ".PNG file",
        "size": "0.46 KB",
        "dateModified": 1694621457.0356534
    },
    {
        "name": "Overwatch/Anqas/Models/000000000801.00C/Textures/80008236B93B.png",
        "type": ".PNG file",
        "size": "0.12 KB",
        "dateModified": 1694621457.0366535
    },
    {
        "name": "Overwatch/Anqas/Models/000000000801.00C/Textures/800087AA8BE9.png",
        "type": ".PNG file",
        "size": "0.23 KB",
        "dateModified": 1694621457.038252
    },
    {
        "name": "Overwatch/Anqas/Models/000000000801.00C/Textures/8000880E6F76.png",
        "type": ".PNG file",
        "size": "0.12 KB",
        "dateModified": 1694621457.0392535
    },
    {
        "name": "Overwatch/Anqas/Models/000000000801.00C/Textures/80008E8245E4.png",
        "type": ".PNG file",
        "size": "0.24 KB",
        "dateModified": 1694621457.0407538
    },
    {
        "name": "Overwatch/Anqas/Models/000000000801.00C/Textures/80009177499B.png",
        "type": ".PNG file",
        "size": "0.11 KB",
        "dateModified": 1694621457.0422559
    },
    {
        "name": "Overwatch/Anqas/Models/000000000801.00C/Textures/800091FFD2BD.png",
        "type": ".PNG file",
        "size": "0.18 KB",
        "dateModified": 1694621457.0427568
    },
    {
        "name": "Overwatch/Anqas/Models/000000000801.00C/Textures/800098A2DE84.png",
        "type": ".PNG file",
        "size": "0.19 KB",
        "dateModified": 1694621457.0442712
    },
    {
        "name": "Overwatch/Anqas/Models/000000000801.00C/Textures/80009AA22259.png",
        "type": ".PNG file",
        "size": "0.40 KB",
        "dateModified": 1694621457.0452714
    },
    {
        "name": "Overwatch/Anqas/Models/000000000801.00C/Textures/80009D3F5DF9.png",
        "type": ".PNG file",
        "size": "0.36 KB",
        "dateModified": 1694621457.046772
    },
    {
        "name": "Overwatch/Anqas/Models/000000000801.00C/Textures/80009E64AD9F.png",
        "type": ".PNG file",
        "size": "0.16 KB",
        "dateModified": 1694621457.0482738
    },
    {
        "name": "Overwatch/Anqas/Models/000000000801.00C/Textures/80009EE28D6D.png",
        "type": ".PNG file",
        "size": "0.33 KB",
        "dateModified": 1694621457.0492835
    },
    {
        "name": "Overwatch/Anqas/Models/000000000801.00C/Textures/8000A64B5218.png",
        "type": ".PNG file",
        "size": "0.37 KB",
        "dateModified": 1694621457.0546849
    },
    {
        "name": "Overwatch/Anqas/Models/000000000801.00C/Textures/8000AB062980.png",
        "type": ".PNG file",
        "size": "0.41 KB",
        "dateModified": 1694621457.0607088
    },
    {
        "name": "Overwatch/Anqas/Models/000000000801.00C/Textures/8000AB2478D0.png",
        "type": ".PNG file",
        "size": "0.14 KB",
        "dateModified": 1694621457.0673194
    },
    {
        "name": "Overwatch/Anqas/Models/000000000801.00C/Textures/8000B3016953.png",
        "type": ".PNG file",
        "size": "0.11 KB",
        "dateModified": 1694621457.0738378
    },
    {
        "name": "Overwatch/Anqas/Models/000000000801.00C/Textures/8000B7D071FD.png",
        "type": ".PNG file",
        "size": "0.18 KB",
        "dateModified": 1694621457.0798702
    },
    {
        "name": "Overwatch/Anqas/Models/000000000801.00C/Textures/8000B89E2EC7.png",
        "type": ".PNG file",
        "size": "0.17 KB",
        "dateModified": 1694621457.084398
    },
    {
        "name": "Overwatch/Anqas/Models/000000000801.00C/Textures/8000B980EC5E.png",
        "type": ".PNG file",
        "size": "0.34 KB",
        "dateModified": 1694621457.0904176
    },
    {
        "name": "Overwatch/Anqas/Models/000000000801.00C/Textures/8000BB3F79BB.png",
        "type": ".PNG file",
        "size": "0.19 KB",
        "dateModified": 1694621457.095932
    },
    {
        "name": "Overwatch/Anqas/Models/000000000801.00C/Textures/8000C0CD23E6.png",
        "type": ".PNG file",
        "size": "0.19 KB",
        "dateModified": 1694621457.1014528
    },
    {
        "name": "Overwatch/Anqas/Models/000000000801.00C/Textures/8000C6295AD1.png",
        "type": ".PNG file",
        "size": "0.42 KB",
        "dateModified": 1694621457.106467
    },
    {
        "name": "Overwatch/Anqas/Models/000000000801.00C/Textures/8000C6E0605D.png",
        "type": ".PNG file",
        "size": "0.22 KB",
        "dateModified": 1694621457.1126702
    },
    {
        "name": "Overwatch/Anqas/Models/000000000801.00C/Textures/8000CF32B9BA.png",
        "type": ".PNG file",
        "size": "0.19 KB",
        "dateModified": 1694621457.1173158
    },
    {
        "name": "Overwatch/Anqas/Models/000000000801.00C/Textures/8000DE9CC62F.png",
        "type": ".PNG file",
        "size": "0.22 KB",
        "dateModified": 1694621457.1243477
    },
    {
        "name": "Overwatch/Anqas/Models/000000000801.00C/Textures/8000DFE33559.png",
        "type": ".PNG file",
        "size": "0.29 KB",
        "dateModified": 1694621457.1302292
    },
    {
        "name": "Overwatch/Anqas/Models/000000000801.00C/Textures/8000E28145A7.png",
        "type": ".PNG file",
        "size": "0.21 KB",
        "dateModified": 1694621457.1372461
    },
    {
        "name": "Overwatch/Anqas/Models/000000000801.00C/Textures/8000E52E01CD.png",
        "type": ".PNG file",
        "size": "0.16 KB",
        "dateModified": 1694621457.1442842
    },
    {
        "name": "Overwatch/Anqas/Models/000000000801.00C/Textures/8000F4C989EF.png",
        "type": ".PNG file",
        "size": "0.12 KB",
        "dateModified": 1694621457.1502397
    },
    {
        "name": "Overwatch/Anqas/Models/000000000801.00C/Textures/8000F6304609.png",
        "type": ".PNG file",
        "size": "0.19 KB",
        "dateModified": 1694621457.1557517
    },
    {
        "name": "Overwatch/Anqas/Models/000000000801.00C/Textures/8000F6610C10.png",
        "type": ".PNG file",
        "size": "0.16 KB",
        "dateModified": 1694621457.1626146
    },
    {
        "name": "Overwatch/Anqas/Models/000000000801.00C/Textures/8000F87DDFCE.png",
        "type": ".PNG file",
        "size": "0.16 KB",
        "dateModified": 1694621457.16719
    },
    {
        "name": "Overwatch/Anqas/Models/000000000801.00C/Textures/8000F975C6BF.png",
        "type": ".PNG file",
        "size": "0.14 KB",
        "dateModified": 1694621457.17264
    },
    {
        "name": "Overwatch/Anqas/Models/000000000801.00C/Textures/8000FA577E0A.png",
        "type": ".PNG file",
        "size": "0.22 KB",
        "dateModified": 1694621457.2161105
    },
    {
        "name": "Overwatch/Anqas/Models/000000000801.00C/Textures/8000FCD654C4.png",
        "type": ".PNG file",
        "size": "0.40 KB",
        "dateModified": 1694621457.2221222
    },
    {
        "name": "Overwatch/Anqas/Models/000000000801.00C/Textures/index.html",
        "type": ".HTML file",
        "size": "2.09 KB",
        "dateModified": 1694621457.2461715
    },
    {
        "name": "Overwatch/Anqas/Models/000000000801.00C/Textures/output.json",
        "type": ".JSON file",
        "size": "23.57 KB",
        "dateModified": 1694621457.2456703
    },
    {
        "name": "Overwatch/Anqas/Models/000000000801.00C/Textures/run.py",
        "type": ".PY file",
        "size": "8.11 KB",
        "dateModified": 1694359229.0680084
    },
    {
        "name": "Overwatch/Anqas/Models/000000000801.00C/Textures/script.js",
        "type": ".JS file",
        "size": "3.07 KB",
        "dateModified": 1694621457.2461715
    }
]