[
    {
        "name": "Amethyst/Effects/0000000052CB.00D/Sounds/000000009968.02C",
        "type": "&lt;DIRECTORY&gt;",
        "size": "N/A",
        "dateModified": 1694702899.3071563
    },
    {
        "name": "Amethyst/Effects/0000000052CB.00D/Sounds/index.html",
        "type": ".HTML file",
        "size": "2.06 KB",
        "dateModified": 1694706529.093225
    },
    {
        "name": "Amethyst/Effects/0000000052CB.00D/Sounds/output.json",
        "type": ".JSON file",
        "size": "0.79 KB",
        "dateModified": 1694706529.093225
    },
    {
        "name": "Amethyst/Effects/0000000052CB.00D/Sounds/script.js",
        "type": ".JS file",
        "size": "3.07 KB",
        "dateModified": 1694706529.0937252
    }
]