[
    {
        "name": "Skin/Overwatch/Overwatch 2/Entities/000000003F54.003/AnimationEffects/00000000AAA2.owanim",
        "type": ".OWANIM file",
        "size": "0.10 KB",
        "dateModified": 1694267304.812531
    },
    {
        "name": "Skin/Overwatch/Overwatch 2/Entities/000000003F54.003/AnimationEffects/00000000ADFE.owanim",
        "type": ".OWANIM file",
        "size": "0.10 KB",
        "dateModified": 1694267304.812531
    },
    {
        "name": "Skin/Overwatch/Overwatch 2/Entities/000000003F54.003/AnimationEffects/00000000AE68.owanim",
        "type": ".OWANIM file",
        "size": "0.10 KB",
        "dateModified": 1694267304.813533
    },
    {
        "name": "Skin/Overwatch/Overwatch 2/Entities/000000003F54.003/AnimationEffects/00000000AE69.owanim",
        "type": ".OWANIM file",
        "size": "0.10 KB",
        "dateModified": 1694267304.813533
    },
    {
        "name": "Skin/Overwatch/Overwatch 2/Entities/000000003F54.003/AnimationEffects/00000000AE6A.owanim",
        "type": ".OWANIM file",
        "size": "0.10 KB",
        "dateModified": 1694267304.814046
    },
    {
        "name": "Skin/Overwatch/Overwatch 2/Entities/000000003F54.003/AnimationEffects/00000000AE6B.owanim",
        "type": ".OWANIM file",
        "size": "0.10 KB",
        "dateModified": 1694267304.8785207
    },
    {
        "name": "Skin/Overwatch/Overwatch 2/Entities/000000003F54.003/AnimationEffects/00000000B0DB.owanim",
        "type": ".OWANIM file",
        "size": "0.10 KB",
        "dateModified": 1694267304.8785207
    },
    {
        "name": "Skin/Overwatch/Overwatch 2/Entities/000000003F54.003/AnimationEffects/00000000B0DC.owanim",
        "type": ".OWANIM file",
        "size": "0.10 KB",
        "dateModified": 1694267304.8790233
    },
    {
        "name": "Skin/Overwatch/Overwatch 2/Entities/000000003F54.003/AnimationEffects/index.html",
        "type": ".HTML file",
        "size": "2.06 KB",
        "dateModified": 1694710805.7759452
    },
    {
        "name": "Skin/Overwatch/Overwatch 2/Entities/000000003F54.003/AnimationEffects/output.json",
        "type": ".JSON file",
        "size": "1.79 KB",
        "dateModified": 1694710805.7435982
    },
    {
        "name": "Skin/Overwatch/Overwatch 2/Entities/000000003F54.003/AnimationEffects/script.js",
        "type": ".JS file",
        "size": "3.07 KB",
        "dateModified": 1694710805.8314672
    }
]