[
    {
        "name": "Overwatch/Qumir/Entities/0000000048CC.003/0000000048CC.003.owentity",
        "type": ".OWENTITY file",
        "size": "0.22 KB",
        "dateModified": 1694267248.6171782
    },
    {
        "name": "Overwatch/Qumir/Entities/0000000048CC.003/AnimationEffects",
        "type": "&lt;DIRECTORY&gt;",
        "size": "N/A",
        "dateModified": 1694704214.4573672
    },
    {
        "name": "Overwatch/Qumir/Entities/0000000048CC.003/index.html",
        "type": ".HTML file",
        "size": "2.06 KB",
        "dateModified": 1694704214.4433107
    },
    {
        "name": "Overwatch/Qumir/Entities/0000000048CC.003/output.json",
        "type": ".JSON file",
        "size": "0.54 KB",
        "dateModified": 1694704214.4433107
    },
    {
        "name": "Overwatch/Qumir/Entities/0000000048CC.003/script.js",
        "type": ".JS file",
        "size": "3.07 KB",
        "dateModified": 1694704214.4438498
    }
]