[
    {
        "name": "HighlightIntro/Overwatch/Kitsune Rush/Models/000000000801.00C/000000000801.owmdl",
        "type": ".OWMDL file",
        "size": "0.75 KB",
        "dateModified": 1694267268.1096392
    },
    {
        "name": "HighlightIntro/Overwatch/Kitsune Rush/Models/000000000801.00C/index.html",
        "type": ".HTML file",
        "size": "2.06 KB",
        "dateModified": 1694713133.1861787
    },
    {
        "name": "HighlightIntro/Overwatch/Kitsune Rush/Models/000000000801.00C/Materials",
        "type": "&lt;DIRECTORY&gt;",
        "size": "N/A",
        "dateModified": 1694281749.3572657
    },
    {
        "name": "HighlightIntro/Overwatch/Kitsune Rush/Models/000000000801.00C/output.json",
        "type": ".JSON file",
        "size": "1.45 KB",
        "dateModified": 1694713133.18568
    },
    {
        "name": "HighlightIntro/Overwatch/Kitsune Rush/Models/000000000801.00C/script.js",
        "type": ".JS file",
        "size": "3.07 KB",
        "dateModified": 1694713133.1861787
    },
    {
        "name": "HighlightIntro/Overwatch/Kitsune Rush/Models/000000000801.00C/test.py",
        "type": ".PY file",
        "size": "1.64 KB",
        "dateModified": 1694272429.4606307
    },
    {
        "name": "HighlightIntro/Overwatch/Kitsune Rush/Models/000000000801.00C/Textures",
        "type": "&lt;DIRECTORY&gt;",
        "size": "N/A",
        "dateModified": 1694342068.5941558
    }
]