[
    {
        "name": "Skin/Season 5/Rogue/Entities/Gameplay3P/Effects/000000000512.00D/index.html",
        "type": ".HTML file",
        "size": "2.06 KB",
        "dateModified": 1694713223.0247324
    },
    {
        "name": "Skin/Season 5/Rogue/Entities/Gameplay3P/Effects/000000000512.00D/output.json",
        "type": ".JSON file",
        "size": "0.21 KB",
        "dateModified": 1694713223.0247324
    },
    {
        "name": "Skin/Season 5/Rogue/Entities/Gameplay3P/Effects/000000000512.00D/script.js",
        "type": ".JS file",
        "size": "3.07 KB",
        "dateModified": 1694713223.0252316
    },
    {
        "name": "Skin/Season 5/Rogue/Entities/Gameplay3P/Effects/000000000512.00D/Sounds",
        "type": "&lt;DIRECTORY&gt;",
        "size": "N/A",
        "dateModified": 1694713223.0262344
    }
]