[
    {
        "name": "Overwatch/Sundown/Models/000000010BAE.00C/Materials/000000002C5C.owmat",
        "type": ".OWMAT file",
        "size": "0.09 KB",
        "dateModified": 1694267261.9483898
    },
    {
        "name": "Overwatch/Sundown/Models/000000010BAE.00C/Materials/index.html",
        "type": ".HTML file",
        "size": "2.06 KB",
        "dateModified": 1694704243.4294195
    },
    {
        "name": "Overwatch/Sundown/Models/000000010BAE.00C/Materials/output.json",
        "type": ".JSON file",
        "size": "0.72 KB",
        "dateModified": 1694704243.4294195
    },
    {
        "name": "Overwatch/Sundown/Models/000000010BAE.00C/Materials/script.js",
        "type": ".JS file",
        "size": "3.07 KB",
        "dateModified": 1694704243.4299214
    }
]