[
    {
        "name": "Kulli/Models/000000000117.118/AnimationEffects/000000000847",
        "type": "&lt;DIRECTORY&gt;",
        "size": "N/A",
        "dateModified": 1694703966.7764647
    },
    {
        "name": "Kulli/Models/000000000117.118/AnimationEffects/000000000957",
        "type": "&lt;DIRECTORY&gt;",
        "size": "N/A",
        "dateModified": 1694703966.7824664
    },
    {
        "name": "Kulli/Models/000000000117.118/AnimationEffects/000000006195",
        "type": "&lt;DIRECTORY&gt;",
        "size": "N/A",
        "dateModified": 1694703966.788479
    },
    {
        "name": "Kulli/Models/000000000117.118/AnimationEffects/00000000D010",
        "type": "&lt;DIRECTORY&gt;",
        "size": "N/A",
        "dateModified": 1694703966.7944925
    },
    {
        "name": "Kulli/Models/000000000117.118/AnimationEffects/00000000D089",
        "type": "&lt;DIRECTORY&gt;",
        "size": "N/A",
        "dateModified": 1694703966.8007073
    },
    {
        "name": "Kulli/Models/000000000117.118/AnimationEffects/00000000D091",
        "type": "&lt;DIRECTORY&gt;",
        "size": "N/A",
        "dateModified": 1694703966.8142295
    },
    {
        "name": "Kulli/Models/000000000117.118/AnimationEffects/00000000D092",
        "type": "&lt;DIRECTORY&gt;",
        "size": "N/A",
        "dateModified": 1694703966.8278437
    },
    {
        "name": "Kulli/Models/000000000117.118/AnimationEffects/00000000D095",
        "type": "&lt;DIRECTORY&gt;",
        "size": "N/A",
        "dateModified": 1694703966.8420167
    },
    {
        "name": "Kulli/Models/000000000117.118/AnimationEffects/00000000D0E4",
        "type": "&lt;DIRECTORY&gt;",
        "size": "N/A",
        "dateModified": 1694703966.852543
    },
    {
        "name": "Kulli/Models/000000000117.118/AnimationEffects/00000000D23F",
        "type": "&lt;DIRECTORY&gt;",
        "size": "N/A",
        "dateModified": 1694703966.8640718
    },
    {
        "name": "Kulli/Models/000000000117.118/AnimationEffects/00000000D2D8",
        "type": "&lt;DIRECTORY&gt;",
        "size": "N/A",
        "dateModified": 1694703966.8745844
    },
    {
        "name": "Kulli/Models/000000000117.118/AnimationEffects/00000000D306",
        "type": "&lt;DIRECTORY&gt;",
        "size": "N/A",
        "dateModified": 1694703966.881086
    },
    {
        "name": "Kulli/Models/000000000117.118/AnimationEffects/00000000D35B",
        "type": "&lt;DIRECTORY&gt;",
        "size": "N/A",
        "dateModified": 1694703966.8865972
    },
    {
        "name": "Kulli/Models/000000000117.118/AnimationEffects/00000000D4A3",
        "type": "&lt;DIRECTORY&gt;",
        "size": "N/A",
        "dateModified": 1694703966.8965254
    },
    {
        "name": "Kulli/Models/000000000117.118/AnimationEffects/00000000D592",
        "type": "&lt;DIRECTORY&gt;",
        "size": "N/A",
        "dateModified": 1694703966.9095175
    },
    {
        "name": "Kulli/Models/000000000117.118/AnimationEffects/00000000D595",
        "type": "&lt;DIRECTORY&gt;",
        "size": "N/A",
        "dateModified": 1694703966.9140308
    },
    {
        "name": "Kulli/Models/000000000117.118/AnimationEffects/00000000D597",
        "type": "&lt;DIRECTORY&gt;",
        "size": "N/A",
        "dateModified": 1694703966.9184587
    },
    {
        "name": "Kulli/Models/000000000117.118/AnimationEffects/00000000DB77",
        "type": "&lt;DIRECTORY&gt;",
        "size": "N/A",
        "dateModified": 1694703966.92446
    },
    {
        "name": "Kulli/Models/000000000117.118/AnimationEffects/00000000DB7D",
        "type": "&lt;DIRECTORY&gt;",
        "size": "N/A",
        "dateModified": 1694703966.9359877
    },
    {
        "name": "Kulli/Models/000000000117.118/AnimationEffects/00000000DD71",
        "type": "&lt;DIRECTORY&gt;",
        "size": "N/A",
        "dateModified": 1694703966.9435616
    },
    {
        "name": "Kulli/Models/000000000117.118/AnimationEffects/00000000DDD2",
        "type": "&lt;DIRECTORY&gt;",
        "size": "N/A",
        "dateModified": 1694703966.9485633
    },
    {
        "name": "Kulli/Models/000000000117.118/AnimationEffects/00000000DEAF",
        "type": "&lt;DIRECTORY&gt;",
        "size": "N/A",
        "dateModified": 1694703966.954117
    },
    {
        "name": "Kulli/Models/000000000117.118/AnimationEffects/00000000DECA",
        "type": "&lt;DIRECTORY&gt;",
        "size": "N/A",
        "dateModified": 1694703966.9601192
    },
    {
        "name": "Kulli/Models/000000000117.118/AnimationEffects/00000000DED9",
        "type": "&lt;DIRECTORY&gt;",
        "size": "N/A",
        "dateModified": 1694703966.9656315
    },
    {
        "name": "Kulli/Models/000000000117.118/AnimationEffects/00000000DF2B",
        "type": "&lt;DIRECTORY&gt;",
        "size": "N/A",
        "dateModified": 1694703966.9711332
    },
    {
        "name": "Kulli/Models/000000000117.118/AnimationEffects/00000000E1AE",
        "type": "&lt;DIRECTORY&gt;",
        "size": "N/A",
        "dateModified": 1694703966.98065
    },
    {
        "name": "Kulli/Models/000000000117.118/AnimationEffects/index.html",
        "type": ".HTML file",
        "size": "2.06 KB",
        "dateModified": 1694706550.839133
    },
    {
        "name": "Kulli/Models/000000000117.118/AnimationEffects/output.json",
        "type": ".JSON file",
        "size": "5.95 KB",
        "dateModified": 1694706550.8386335
    },
    {
        "name": "Kulli/Models/000000000117.118/AnimationEffects/script.js",
        "type": ".JS file",
        "size": "3.07 KB",
        "dateModified": 1694706550.839133
    }
]