[
    {
        "name": "Overwatch/Qumir/Effects/000000004E23.00D/Sounds/00000000A569.02C/0000002318E3.03F.ogg",
        "type": ".OGG file",
        "size": "141.76 KB",
        "dateModified": 1694267248.3770776
    },
    {
        "name": "Overwatch/Qumir/Effects/000000004E23.00D/Sounds/00000000A569.02C/index.html",
        "type": ".HTML file",
        "size": "2.06 KB",
        "dateModified": 1694704213.099005
    },
    {
        "name": "Overwatch/Qumir/Effects/000000004E23.00D/Sounds/00000000A569.02C/output.json",
        "type": ".JSON file",
        "size": "0.40 KB",
        "dateModified": 1694704213.098506
    },
    {
        "name": "Overwatch/Qumir/Effects/000000004E23.00D/Sounds/00000000A569.02C/script.js",
        "type": ".JS file",
        "size": "3.07 KB",
        "dateModified": 1694704213.099005
    }
]