[
    {
        "name": "Entities/000000004C2A.003/000000004C2A.003.owentity",
        "type": ".OWENTITY file",
        "size": "0.13 KB",
        "dateModified": 1694267263.3842947
    },
    {
        "name": "Entities/000000004C2A.003/index.html",
        "type": ".HTML file",
        "size": "2.09 KB",
        "dateModified": 1694360700.9590719
    },
    {
        "name": "Entities/000000004C2A.003/output.json",
        "type": ".JSON file",
        "size": "0.94 KB",
        "dateModified": 1694697651.0930138
    },
    {
        "name": "Entities/000000004C2A.003/run.py",
        "type": ".PY file",
        "size": "8.11 KB",
        "dateModified": 1694359229.0680084
    },
    {
        "name": "Entities/000000004C2A.003/script.js",
        "type": ".JS file",
        "size": "3.07 KB",
        "dateModified": 1694360700.959573
    }
]